nightcrawler/__init__.py
nightcrawler/crawler.py
nightcrawler/matchers.py
nightcrawler/page.py
nightcrawler/request.py
nightcrawler/sitemap.py
nightcrawler/utils.py
NightCrawler-0.1.6.dist-info/LICENSE
NightCrawler-0.1.6.dist-info/METADATA
NightCrawler-0.1.6.dist-info/WHEEL
NightCrawler-0.1.6.dist-info/entry_points.txt
NightCrawler-0.1.6.dist-info/top_level.txt
NightCrawler-0.1.6.dist-info/zip-safe
NightCrawler-0.1.6.dist-info/RECORD
