Metadata-Version: 2.1
Name: NightCrawler
Version: 0.1.6
Summary: Website crawling bot
Home-page: https://github.com/szczad/NightCrawler
Author: Grzeoorz Szczudlik
Author-email: 2914011+szczad@users.noreply.github.com
License: MIT
Keywords: crawler spider website
Platform: UNKNOWN
Classifier: Development Status :: 3 - Alpha
Classifier: License :: OSI Approved :: MIT License
Classifier: Programming Language :: Python :: 3.2
Requires-Dist: beautifulsoup4
Requires-Dist: requests
Requires-Dist: lxml
Requires-Dist: validators
